real/__init__.py
real/hello/__init__.py
real/hello/message.py
cfr_real-0.1.dist-info/METADATA
cfr_real-0.1.dist-info/WHEEL
cfr_real-0.1.dist-info/top_level.txt
cfr_real-0.1.dist-info/RECORD
