Metadata-Version: 2.1
Name: cfr-real
Version: 0.1
Summary: cfr,dsh,dyl are a group
Author: cfr
License: UNKNOWN
Platform: UNKNOWN
